CHANGELOG.txt
MANIFEST.in
README.txt
setup.py
DisTop/__init__.py
DisTop.egg-info/PKG-INFO
DisTop.egg-info/SOURCES.txt
DisTop.egg-info/dependency_links.txt
DisTop.egg-info/requires.txt
DisTop.egg-info/top_level.txt