Metadata-Version: 2.1
Name: DisTop
Version: 1.0.1
Summary: Very easy to use https://distop.xyz Stats updater
Home-page: UNKNOWN
Author: MrStretch
Author-email: markustraus@gmail.com
License: MIT
Keywords: distop,botlist,discord bots,bots
Platform: UNKNOWN
Classifier: Development Status :: 5 - Production/Stable
Classifier: Intended Audience :: Education
Classifier: Operating System :: Microsoft :: Windows :: Windows 10
Classifier: License :: OSI Approved :: MIT License
Classifier: Programming Language :: Python :: 3
